{"assets":{"4D69599EA966FDB0E61E47EF0C8BDC31":{"type":"texture","index":16,"assetRequest":{"type":"slide","state":"outgoing","slide":"A005A2A6-7B28-4B3D-B268-FDF32EBFFF14"},"url":"assets/4D69599EA966FDB0E61E47EF0C8BDC31.svg","width":1920,"height":1080},"DE398D12A7E40E811788B493D966F53C":{"type":"texture","index":17,"assetRequest":{"type":"slide","state":"incoming","slide":"3A4FEE44-229D-4996-997A-C893EC7515BC"},"url":"assets/DE398D12A7E40E811788B493D966F53C.svg","width":1920,"height":1080}},"events":[{"effects":[{"beginTime":0,"baseLayer":{"animations":[],"initialState":{"affineTransform":[1,0,0,1,0,0],"masksToBounds":true,"rotation":0,"scale":1,"position":{"pointX":960,"pointY":540},"width":1920,"sublayerTransform":[1,0,0,0,0,1,0,0,0,0,1,0,0,0,0,1],"contentsRect":{"y":0,"x":0,"width":1,"height":1},"opacity":1,"edgeAntialiasingMask":0,"height":1080,"hidden":false,"anchorPoint":{"pointX":0.5,"pointY":0.5}},"objectID":"0","layers":[{"animations":[],"initialState":{"affineTransform":[1,0,0,1,0,0],"masksToBounds":false,"rotation":0,"scale":1,"position":{"pointX":960,"pointY":540},"width":1920,"sublayerTransform":[1,0,0,0,0,1,0,0,0,0,1,-0.0003500791246677598,0,0,0,1],"contentsRect":{"y":0,"x":0,"width":1,"height":1},"opacity":1,"edgeAntialiasingMask":15,"height":1080,"hidden":false,"anchorPoint":{"pointX":0.5,"pointY":0.5}},"layers":[{"animations":[],"layers":[],"initialState":{"affineTransform":[1,0,0,1,0,0],"masksToBounds":false,"rotation":0,"scale":1,"position":{"pointX":960,"pointY":540},"width":1920,"sublayerTransform":[1,0,0,0,0,1,0,0,0,0,1,0,0,0,0,1],"contentsRect":{"y":0,"x":0,"width":1,"height":1},"opacity":1,"edgeAntialiasingMask":0,"height":1080,"hidden":false,"anchorPoint":{"pointX":0.5,"pointY":0.5}},"texture":"DE398D12A7E40E811788B493D966F53C"},{"animations":[{"from":{"scalar":false},"beginTime":0,"repeatCount":0,"fillMode":"both","property":"hidden","duration":0.01,"to":{"scalar":true}}],"layers":[],"initialState":{"affineTransform":[1,0,0,1,0,0],"masksToBounds":false,"rotation":0,"scale":1,"position":{"pointX":960,"pointY":540},"width":1920,"sublayerTransform":[1,0,0,0,0,1,0,0,0,0,1,0,0,0,0,1],"contentsRect":{"y":0,"x":0,"width":1,"height":1},"opacity":1,"edgeAntialiasingMask":0,"height":1080,"hidden":false,"anchorPoint":{"pointX":0.5,"pointY":0.5}},"texture":"4D69599EA966FDB0E61E47EF0C8BDC31"}]}]},"effects":[],"duration":0.01,"type":"transition","name":"none","objectID":"0"}],"automaticPlay":false,"hyperlinks":[],"accessibility":[{"text":"pasted-image.png","targetRectangle":{"y":205.5,"x":139.6597900390625,"width":550,"height":825}},{"text":"Recipe for Mac & Cheese","targetRectangle":{"y":107.2572017908096,"x":139.6683483123779,"width":580.81484375,"height":60.00076293945312}},{"text":"Ingredients for Mac & Cheese","targetRectangle":{"y":107.2572017908096,"x":1004.525190353394,"width":686.3324218750001,"height":60.00076293945312}},{"text":"1 lb of macaroni shells","targetRectangle":{"y":240.0000038146973,"x":1097.210934638977,"width":502.0500000000002,"height":120}},{"text":"4 cups of whole milk","targetRectangle":{"y":360.0000038146973,"x":1097.210934638977,"width":455.7,"height":120}},{"text":"8 tbsp of unsalted butter","targetRectangle":{"y":480.0000038146973,"x":1097.210934638977,"width":547.45,"height":120}},{"text":"8 oz of cheddar cheese","targetRectangle":{"y":600.0000038146973,"x":1097.210934638977,"width":530.8500000000001,"height":120}},{"text":"3 oz of Pecorino Romano cheese","targetRectangle":{"y":720.0000038146973,"x":1097.210934638977,"width":575.3000000000002,"height":120}}],"baseLayer":{"animations":[],"initialState":{"affineTransform":[1,0,0,1,0,0],"masksToBounds":true,"rotation":0,"scale":1,"position":{"pointX":960,"pointY":540},"width":1920,"sublayerTransform":[1,0,0,0,0,1,0,0,0,0,1,0,0,0,0,1],"contentsRect":{"y":0,"x":0,"width":1,"height":1},"opacity":1,"edgeAntialiasingMask":0,"height":1080,"hidden":false,"anchorPoint":{"pointX":0.5,"pointY":0.5}},"objectID":"0","layers":[{"animations":[],"initialState":{"affineTransform":[1,0,0,1,0,0],"masksToBounds":false,"rotation":0,"scale":1,"position":{"pointX":960,"pointY":540},"width":1920,"sublayerTransform":[1,0,0,0,0,1,0,0,0,0,1,-0.0003500791246677598,0,0,0,1],"contentsRect":{"y":0,"x":0,"width":1,"height":1},"opacity":1,"edgeAntialiasingMask":15,"height":1080,"hidden":false,"anchorPoint":{"pointX":0.5,"pointY":0.5}},"layers":[{"animations":[],"layers":[],"initialState":{"affineTransform":[1,0,0,1,0,0],"masksToBounds":false,"rotation":0,"scale":1,"position":{"pointX":960,"pointY":540},"width":1920,"sublayerTransform":[1,0,0,0,0,1,0,0,0,0,1,0,0,0,0,1],"contentsRect":{"y":0,"x":0,"width":1,"height":1},"opacity":1,"edgeAntialiasingMask":0,"height":1080,"hidden":false,"anchorPoint":{"pointX":0.5,"pointY":0.5}},"texture":"4D69599EA966FDB0E61E47EF0C8BDC31"}]}]}}]}